{
    "functions": [
        {
            "name": "stake",
            "type": "Function",
            "payable": false,
            "onlyOwner": false,
            "inputs": [],
            "outputs": [
                {
                    "name": "success",
                    "type": "BOOL"
                }
            ]
        },
        {
            "name": "unstake",
            "type": "Function",
            "payable": false,
            "onlyOwner": false,
            "inputs": [],
            "outputs": [
                {
                    "name": "success",
                    "type": "BOOL"
                }
            ]
        },
        {
            "name": "getRewards",
            "type": "Function",
            "payable": false,
            "onlyOwner": false,
            "inputs": [],
            "outputs": [
                {
                    "name": "pending",
                    "type": "UINT256"
                }
            ]
        },
        {
            "name": "getStakeBalance",
            "type": "Function",
            "payable": false,
            "onlyOwner": false,
            "inputs": [],
            "outputs": [
                {
                    "name": "balance",
                    "type": "UINT256"
                }
            ]
        },
        {
            "name": "claim",
            "type": "Function",
            "payable": false,
            "onlyOwner": false,
            "inputs": [],
            "outputs": [
                {
                    "name": "reward",
                    "type": "UINT256"
                }
            ]
        }
    ],
    "events": []
}